crawler/__init__.py
crawler/drivers/chromedriver.exe
crawler/items.py
crawler/middlewares.py
crawler/parsers/LMUParser.py
crawler/parsers/__init__.py
crawler/pipelines.py
crawler/settings.py
crawler/spiders/__init__.py
crawler/spiders/lmu.py
crawler/spiders/tum.py
digital_literacy-0.1.0.dist-info/LICENSE.txt
digital_literacy-0.1.0.dist-info/WHEEL
digital_literacy-0.1.0.dist-info/METADATA
digital_literacy-0.1.0.dist-info/RECORD
