Metadata-Version: 2.1
Name: digital-literacy
Version: 0.1.0
Summary: Level at which course modules of German/Bavarian universities teach about Digitalization
Author: Sanjay Jayaprakash
Author-email: sanjay.jayaprakash@tum.de
Requires-Python: >=3.8,<4.0
Classifier: Programming Language :: Python :: 3
Classifier: Programming Language :: Python :: 3.10
Classifier: Programming Language :: Python :: 3.8
Classifier: Programming Language :: Python :: 3.9
Requires-Dist: black (>=22.6.0,<23.0.0)
Requires-Dist: bs4
Requires-Dist: hyperopt (>=0.2.7,<0.3.0)
Requires-Dist: jupyter
Requires-Dist: matplotlib (>=3.4.3,<4.0.0)
Requires-Dist: nltk (>=3.6.5,<4.0.0)
Requires-Dist: pandas (>=1.3.4,<2.0.0)
Requires-Dist: pymupdf (>=1.20.0,<2.0.0)
Requires-Dist: pytest (>=7.1.2,<8.0.0)
Requires-Dist: scrapy (>=2.6.1,<3.0.0)
Requires-Dist: selenium (>=3.141.0,<4.0.0)
Requires-Dist: sklearn
Requires-Dist: tqdm (>=4.62.3,<5.0.0)
